{
    "generation": 8,
    "number": "811",
    "defaultName": "Thwackey",
    "types": [
        "grass"
    ],
    "forms": [
        "Thwackey"
    ],
    "formsDetails": {
        "thwackey": {
            "name": "Thwackey",
            "stats": {
                "hp": {
                    "base": "70",
                    "min": "250",
                    "max": "344"
                },
                "attack": {
                    "base": "85",
                    "min": "157",
                    "max": "295"
                },
                "defense": {
                    "base": "70",
                    "min": "130",
                    "max": "262"
                },
                "spAtk": {
                    "base": "55",
                    "min": "103",
                    "max": "229"
                },
                "spDef": {
                    "base": "60",
                    "min": "112",
                    "max": "240"
                },
                "speed": {
                    "base": "80",
                    "min": "148",
                    "max": "284"
                }
            },
            "info": {
                "number": "811",
                "species": "Beat Pokémon",
                "height": "0.7 m (2′04″)",
                "weight": "14.0 kg (30.9 lbs)",
                "types": [
                    "grass"
                ],
                "abilities": [
                    {
                        "name": "Overgrow",
                        "isHidden": false
                    },
                    {
                        "name": "Grassy Surge",
                        "isHidden": true
                    }
                ]
            }
        }
    }
}